forestadmin/datasource_toolkit/__init__.py
forestadmin/datasource_toolkit/collections.py
forestadmin/datasource_toolkit/context/__init__.py
forestadmin/datasource_toolkit/context/agent_context.py
forestadmin/datasource_toolkit/context/collection_context.py
forestadmin/datasource_toolkit/context/relaxed_wrappers/__init__.py
forestadmin/datasource_toolkit/context/relaxed_wrappers/collection.py
forestadmin/datasource_toolkit/datasource_customizer/collection_customizer.py
forestadmin/datasource_toolkit/datasource_customizer/datasource_composite.py
forestadmin/datasource_toolkit/datasource_customizer/datasource_customizer.py
forestadmin/datasource_toolkit/datasource_customizer/types.py
forestadmin/datasource_toolkit/datasources.py
forestadmin/datasource_toolkit/decorators/__init__.py
forestadmin/datasource_toolkit/decorators/action/__init__.py
forestadmin/datasource_toolkit/decorators/action/collections.py
forestadmin/datasource_toolkit/decorators/action/context/__init__.py
forestadmin/datasource_toolkit/decorators/action/context/base.py
forestadmin/datasource_toolkit/decorators/action/context/bulk.py
forestadmin/datasource_toolkit/decorators/action/context/single.py
forestadmin/datasource_toolkit/decorators/action/form_elements.py
forestadmin/datasource_toolkit/decorators/action/result_builder.py
forestadmin/datasource_toolkit/decorators/action/types/__init__.py
forestadmin/datasource_toolkit/decorators/action/types/actions.py
forestadmin/datasource_toolkit/decorators/action/types/fields.py
forestadmin/datasource_toolkit/decorators/action/types/widgets.py
forestadmin/datasource_toolkit/decorators/binary/__init__.py
forestadmin/datasource_toolkit/decorators/binary/collection.py
forestadmin/datasource_toolkit/decorators/binary/utils.py
forestadmin/datasource_toolkit/decorators/chart/__init__.py
forestadmin/datasource_toolkit/decorators/chart/chart_collection_decorator.py
forestadmin/datasource_toolkit/decorators/chart/chart_datasource_decorator.py
forestadmin_datasource_toolkit-1.23.9.dist-info/METADATA
forestadmin_datasource_toolkit-1.23.9.dist-info/WHEEL
forestadmin_datasource_toolkit-1.23.9.dist-info/RECORD
