Metadata-Version: 2.4
Name: forestadmin-datasource-toolkit
Version: 1.23.9
Summary: datasource toolkit for forestadmin python agent
Author: Valentin Monté
Author-email: valentinm@forestadmin.com
Requires-Python: >=3.8,<3.14
Classifier: Programming Language :: Python :: 3
Classifier: Programming Language :: Python :: 3.8
Classifier: Programming Language :: Python :: 3.9
Classifier: Programming Language :: Python :: 3.10
Classifier: Programming Language :: Python :: 3.11
Classifier: Programming Language :: Python :: 3.12
Classifier: Programming Language :: Python :: 3.13
Requires-Dist: backports.zoneinfo[tzdata] (>=0.2.1,<0.3.0) ; python_version < "3.9"
Requires-Dist: filetype (>=1.0.0,<2.0.0)
Requires-Dist: numpy (>=1.24.0) ; python_full_version >= "3.8.0" and python_version < "3.12"
Requires-Dist: numpy (>=1.3.0) ; python_version >= "3.13"
Requires-Dist: pandas (>=1.4.0) ; python_full_version < "3.13.0"
Requires-Dist: pandas (>=2.2.3) ; python_full_version >= "3.13.0"
Requires-Dist: typing-extensions (>=4.2,<5.0)
Project-URL: Documentation, https://docs.forestadmin.com/developer-guide-agents-python/
Project-URL: Homepage, https://www.forestadmin.com
Project-URL: Repository, https://github.com/ForestAdmin/agent-python
